co_citation.py
co_citation-0.7.dist-info/LICENSE.txt
co_citation-0.7.dist-info/METADATA
co_citation-0.7.dist-info/WHEEL
co_citation-0.7.dist-info/top_level.txt
co_citation-0.7.dist-info/RECORD
