Metadata-Version: 2.1
Name: co-citation
Version: 0.7
Summary: Create a co-citation graph from a list of papers
Home-page: https://pypi.org/project/co-citation/
Author: Vincent Lequertier
Author-email: vi.le@autistici.org
License: UNKNOWN
Project-URL: Bug Reports, https://gitlab.com/vi.le/co-citation/-/issues
Project-URL: Documentation, http://vi.le.gitlab.io/co-citation/
Project-URL: Source, https://gitlab.com/vi.le/co-citation
Keywords: co-citation research literature-review
Platform: UNKNOWN
Classifier: Development Status :: 3 - Alpha
Classifier: Intended Audience :: Science/Research
Classifier: Topic :: Scientific/Engineering :: Artificial Intelligence
Classifier: License :: OSI Approved :: GNU General Public License v3 (GPLv3)
Classifier: Programming Language :: Python :: 3
Classifier: Programming Language :: Python :: 3.5
Classifier: Programming Language :: Python :: 3.6
Classifier: Programming Language :: Python :: 3.7
Classifier: Programming Language :: Python :: 3.8
Requires-Python: >=3.5, <4
